lexiconalgorithm/__init__.py
lexiconalgorithm/booster.py
lexiconalgorithm/emoticon.py
lexiconalgorithm/emotion_new.csv
lexiconalgorithm/neg.txt
lexiconalgorithm/neg1.txt
lexiconalgorithm/sentileye.py
lexiconalgorithm/sentileye_list.csv
lexiconalgorithm/slang.csv
sentileye/__init__.py
sentileye/booster.py
sentileye/emoticon.py
sentileye/emotion_new.csv
sentileye/neg.txt
sentileye/neg1.txt
sentileye/polarity.py
sentileye/sentileye_list.csv
sentileye/slang.csv
SentileyeClassifer-0.2.dist-info/LICENSE.txt
SentileyeClassifer-0.2.dist-info/METADATA
SentileyeClassifer-0.2.dist-info/WHEEL
SentileyeClassifer-0.2.dist-info/top_level.txt
SentileyeClassifer-0.2.dist-info/RECORD
